dynamic_favicon/__init__.py
dynamic_favicon/favicon_rotator.py
dynamic_favicon/favicon_sources.py
dynamic_favicon/scheduler.py
dynamic_favicon-1.0.0.dist-info/licenses/LICENSE
dynamic_favicon-1.0.0.dist-info/METADATA
dynamic_favicon-1.0.0.dist-info/WHEEL
dynamic_favicon-1.0.0.dist-info/top_level.txt
dynamic_favicon-1.0.0.dist-info/RECORD
