Metadata-Version: 2.4
Name: dynamic-favicon
Version: 1.0.0
Summary: A Python module for automatically rotating website favicons based on time intervals
Author-email: Sanjay Choudhary <sanjay@mailchat.me>
License: MIT
Project-URL: Homepage, https://github.com/cu-sanjay/DynamicFavicon
Project-URL: Bug Reports, https://github.com/cu-sanjay/DynamicFavicon/issues
Project-URL: Source, https://github.com/cu-sanjay/DynamicFavicon
Project-URL: Documentation, https://github.com/cu-sanjay/DynamicFavicon#readme
Keywords: favicon,dynamic,rotation,website,emoji,icons
Classifier: Development Status :: 5 - Production/Stable
Classifier: Intended Audience :: Developers
Classifier: Topic :: Software Development :: Libraries :: Python Modules
Classifier: Topic :: Internet :: WWW/HTTP :: Dynamic Content
Classifier: License :: OSI Approved :: MIT License
Classifier: Programming Language :: Python :: 3
Classifier: Programming Language :: Python :: 3.8
Classifier: Programming Language :: Python :: 3.9
Classifier: Programming Language :: Python :: 3.10
Classifier: Programming Language :: Python :: 3.11
Classifier: Programming Language :: Python :: 3.12
Requires-Python: >=3.8
License-File: LICENSE
Requires-Dist: schedule>=1.2.0
Requires-Dist: Pillow>=9.1.0
Requires-Dist: requests>=2.25.0
Provides-Extra: dev
Requires-Dist: flask>=2.0.0; extra == "dev"
Requires-Dist: build>=0.8.0; extra == "dev"
Requires-Dist: setuptools>=61.0; extra == "dev"
Requires-Dist: wheel>=0.37.0; extra == "dev"
Requires-Dist: twine>=4.0.0; extra == "dev"
Dynamic: license-file
